monasca_tempest_tests/README.md
monasca_tempest_tests/__init__.py
monasca_tempest_tests/config.py
monasca_tempest_tests/plugin.py
monasca_tempest_tests/clients/__init__.py
monasca_tempest_tests/clients/api.py
monasca_tempest_tests/clients/event_api.py
monasca_tempest_tests/clients/log_api.py
monasca_tempest_tests/contrib/gate_hook.sh
monasca_tempest_tests/contrib/post_test_hook.sh
monasca_tempest_tests/services/__init__.py
monasca_tempest_tests/services/elasticsearch_client.py
monasca_tempest_tests/services/events_api_client.py
monasca_tempest_tests/services/log_api_v3_client.py
monasca_tempest_tests/services/monasca_client.py
monasca_tempest_tests/tests/__init__.py
monasca_tempest_tests/tests/api/__init__.py
monasca_tempest_tests/tests/api/base.py
monasca_tempest_tests/tests/api/constants.py
monasca_tempest_tests/tests/api/helpers.py
monasca_tempest_tests/tests/api/test_alarm_definitions.py
monasca_tempest_tests/tests/api/test_alarm_state_history_multiple_transitions.py
monasca_tempest_tests/tests/api/test_alarm_transitions.py
monasca_tempest_tests/tests/api/test_alarms.py
monasca_tempest_tests/tests/api/test_alarms_count.py
monasca_tempest_tests/tests/api/test_alarms_state_history_one_transition.py
monasca_tempest_tests/tests/api/test_dimensions.py
monasca_tempest_tests/tests/api/test_measurements.py
monasca_tempest_tests/tests/api/test_metrics.py
monasca_tempest_tests/tests/api/test_metrics_names.py
monasca_tempest_tests/tests/api/test_notification_method_type.py
monasca_tempest_tests/tests/api/test_notification_methods.py
monasca_tempest_tests/tests/api/test_read_only_role.py
monasca_tempest_tests/tests/api/test_statistics.py
monasca_tempest_tests/tests/api/test_versions.py
monasca_tempest_tests/tests/event_api/__init__.py
monasca_tempest_tests/tests/event_api/base.py
monasca_tempest_tests/tests/event_api/test_simple.py
monasca_tempest_tests/tests/log_api/__init__.py
monasca_tempest_tests/tests/log_api/base.py
monasca_tempest_plugin-2.7.0.dist-info/AUTHORS
monasca_tempest_plugin-2.7.0.dist-info/LICENSE
monasca_tempest_plugin-2.7.0.dist-info/METADATA
monasca_tempest_plugin-2.7.0.dist-info/WHEEL
monasca_tempest_plugin-2.7.0.dist-info/entry_points.txt
monasca_tempest_plugin-2.7.0.dist-info/pbr.json
monasca_tempest_plugin-2.7.0.dist-info/top_level.txt
monasca_tempest_plugin-2.7.0.dist-info/RECORD
