Metadata-Version: 2.1
Name: monasca-tempest-plugin
Version: 2.7.0
Summary: Tempest plugin for Monasca project
Home-page: https://docs.openstack.org/monasca-api/latest/
Author: OpenStack
Author-email: openstack-discuss@lists.openstack.org
License: UNKNOWN
Platform: UNKNOWN
Classifier: Environment :: OpenStack
Classifier: Intended Audience :: Information Technology
Classifier: Intended Audience :: System Administrators
Classifier: License :: OSI Approved :: Apache Software License
Classifier: Operating System :: POSIX :: Linux
Classifier: Programming Language :: Python
Classifier: Programming Language :: Python :: 3
Classifier: Programming Language :: Python :: 3.5
Classifier: Programming Language :: Python :: 3.6
Classifier: Programming Language :: Python :: 3.7
Classifier: Programming Language :: Python :: 3.8
Classifier: Topic :: System :: Monitoring
Requires-Dist: mock (>=2.0.0)
Requires-Dist: monasca-common (>=2.8.0)
Requires-Dist: oslo.config (>=5.2.0)
Requires-Dist: oslo.serialization (!=2.19.1,>=2.18.0)
Requires-Dist: oslo.utils (>=3.33.0)
Requires-Dist: oslotest (>=3.2.0)
Requires-Dist: pbr (!=2.1.0,>=2.0.0)
Requires-Dist: tempest (>=17.1.0)
